MANIFEST.in
setup.py
gtmetrix/__init__.py
gtmetrix/interface.py
gtmetrix/settings.py
gtmetrix/utils.py
python_gtmetrix.egg-info/PKG-INFO
python_gtmetrix.egg-info/SOURCES.txt
python_gtmetrix.egg-info/dependency_links.txt
python_gtmetrix.egg-info/not-zip-safe
python_gtmetrix.egg-info/requires.txt
python_gtmetrix.egg-info/top_level.txt