Metadata-Version: 1.1
Name: python-gtmetrix
Version: 0.2.2
Summary: A Python client library for GTmetrix REST API.
Home-page: https://github.com/aisayko/python-gtmetrix
Author: Alex Isayko
Author-email: alex.isayko@gmail.com
License: MIT License
Keywords: python gtmetrix performance pagespeed yslow
Platform: any
Classifier: Development Status :: 5 - Production/Stable
Classifier: Environment :: Web Environment
Classifier: Intended Audience :: Developers
Classifier: License :: OSI Approved :: MIT License
Classifier: Operating System :: OS Independent
Classifier: Programming Language :: Python
Classifier: Topic :: Software Development :: Libraries :: Python Modules
